hantekosc/__init__.py
hantekosc/channel.py
hantekosc/devices.py
hantekosc/oscilloscope.py
hantekosc/c_code/__init__.py
hantekosc/c_code/c_code.py
hantekosc/c_code/triggering.c
hantekosc/c_code/triggering.h
hantekosc/py_ht6022/LibUsbScope.py
hantekosc/py_ht6022/__init__.py
hantekosc/py_ht6022/Firmware/README.md
hantekosc/py_ht6022/Firmware/__init__.py
hantekosc/py_ht6022/Firmware/dso602x_fw_version.h
hantekosc/py_ht6022/Firmware/firmware_packet_dump.csv
hantekosc/py_ht6022/Firmware/DDS120/Makefile
hantekosc/py_ht6022/Firmware/DDS120/dds120-firmware.hex
hantekosc/py_ht6022/Firmware/DDS120/dds120.c
hantekosc/py_ht6022/Firmware/DDS120/descriptor.asm
hantekosc/py_ht6022/Firmware/DDS120/fl_fw.sh
hantekosc/py_ht6022/Firmware/DSO6021/Makefile
hantekosc/py_ht6022/Firmware/DSO6021/descriptor.asm
hantekosc/py_ht6022/Firmware/DSO6021/dso6021-firmware.hex
hantekosc/py_ht6022/Firmware/DSO6021/dso6021.c
hantekosc/py_ht6022/Firmware/DSO6021/fl_fw.sh
hantekosc/py_ht6022/Firmware/DSO6022BE/Makefile
hantekosc/py_ht6022/Firmware/DSO6022BE/descriptor.asm
hantekosc/py_ht6022/Firmware/DSO6022BE/descriptor.inc
hantekosc/py_ht6022/Firmware/DSO6022BE/dso6022be-firmware.hex
hantekosc/py_ht6022/Firmware/DSO6022BE/dso6022be.c
hantekosc/py_ht6022/Firmware/DSO6022BE/fl_fw.sh
hantekosc/py_ht6022/Firmware/DSO6022BE/fx2.mk
hantekosc/py_ht6022/Firmware/DSO6022BE/scope6022.inc
hantekosc/py_ht6022/Firmware/DSO6022BE/waveforms.inc
hantekosc/py_ht6022/Firmware/DSO6022BE/waveforms/COMPILE_GPIF.sh
hantekosc/py_ht6022/Firmware/DSO6022BE/waveforms/gpif_1.inc
hantekosc/py_ht6022/Firmware/DSO6022BE/waveforms/gpif_1.wvf
hantekosc/py_ht6022/Firmware/DSO6022BE/waveforms/gpif_10.inc
hantekosc/py_ht6022/Firmware/DSO6022BE/waveforms/gpif_10.wvf
hantekosc/py_ht6022/Firmware/DSO6022BE/waveforms/gpif_102.inc
hantekosc/py_ht6022/Firmware/DSO6022BE/waveforms/gpif_102.wvf
hantekosc/py_ht6022/Firmware/DSO6022BE/waveforms/gpif_103.inc
hantekosc/py_ht6022/Firmware/DSO6022BE/waveforms/gpif_103.wvf
hantekosc-0.1.1.dist-info/LICENSE
hantekosc-0.1.1.dist-info/METADATA
hantekosc-0.1.1.dist-info/WHEEL
hantekosc-0.1.1.dist-info/top_level.txt
hantekosc-0.1.1.dist-info/RECORD
