Metadata-Version: 2.1
Name: hantekosc
Version: 0.1.1
Summary: Python interface with integrated software trigger for controlling USB oscilloscopes from Hantek.
Author-email: Bruno Mecke <info@bmecke.de>
License: OSI Approved :: GNU General Public License v3 (GPLv3)
Project-URL: Homepage, https://github.com/BMecke/hantekosc
Keywords: oscilloscope,software-trigger,hantek,6022BE,6022BL
Classifier: Programming Language :: Python :: 3
Classifier: Operating System :: POSIX :: Linux
Classifier: Development Status :: 4 - Beta
Classifier: Intended Audience :: Science/Research
Classifier: Topic :: Scientific/Engineering
Requires-Python: >=3.10
License-File: LICENSE
Requires-Dist: numpy
Requires-Dist: cffi
Requires-Dist: libusb1
Provides-Extra: doc
Requires-Dist: Sphinx ; extra == 'doc'
Requires-Dist: sphinx-rtd-theme ; extra == 'doc'
Provides-Extra: example
Requires-Dist: matplotlib ; extra == 'example'
